[
  {
    "0":"desconhecido",
    "1":"desconhecido",
    "2":"não",
    "3":"não",
    "4":"sim",
    "5":"não",
    "6":"não",
    "7":"não",
    "8":"não",
    "9":"não",
    "10":"não",
    "11":"desconhecido",
    "12":"sim",
    "13":"sim",
    "14":"sim",
    "15":"sim",
    "16":"não",
    "17":"sim",
    "18":"não",
    "19":"não",
    "20":"não",
    "21":"não",
    "22":"não",
    "23":"não",
    "24":"não",
    "25":"sim",
    "Personagem":"abu"
  },
  {
    "0":"sim",
    "1":"não",
    "2":"sim",
    "3":"não",
    "4":"não",
    "5":"não",
    "6":"sim",
    "7":"não",
    "8":"não",
    "9":"não",
    "10":"não",
    "11":"sim",
    "12":"não",
    "13":"sim",
    "14":"sim",
    "15":"sim",
    "16":"sim",
    "17":"não",
    "18":"sim",
    "19":"não",
    "20":"não",
    "21":"não",
    "22":"não",
    "23":"sim",
    "24":"não",
    "25":"não",
    "Personagem":"alladin"
  },
  {
    "0":"não",
    "1":"sim",
    "2":"sim",
    "3":"não",
    "4":"não",
    "5":"sim",
    "6":"não",
    "7":"não",
    "8":"não",
    "9":"não",
    "10":"não",
    "11":"não",
    "12":"não",
    "13":"não",
    "14":"sim",
    "15":"sim",
    "16":"não",
    "17":"não",
    "18":"sim",
    "19":"não",
    "20":"não",
    "21":"não",
    "22":"não",
    "23":"sim",
    "24":"não",
    "25":"não",
    "Personagem":"alice"
  },
  {
    "0":"não",
    "1":"sim",
    "2":"sim",
    "3":"não",
    "4":"não",
    "5":"sim",
    "6":"não",
    "7":"não",
    "8":"não",
    "9":"não",
    "10":"não",
    "11":"não",
    "12":"não",
    "13":"não",
    "14":"sim",
    "15":"sim",
    "16":"não",
    "17":"não",
    "18":"sim",
    "19":"não",
    "20":"não",
    "21":"não",
    "22":"não",
    "23":"não",
    "24":"não",
    "25":"não",
    "Personagem":"anna"
  },
  {
    "0":"não",
    "1":"sim",
    "2":"não",
    "3":"não",
    "4":"não",
    "5":"sim",
    "6":"não",
    "7":"não",
    "8":"não",
    "9":"não",
    "10":"não",
    "11":"sim",
    "12":"não",
    "13":"sim",
    "14":"sim",
    "15":"sim",
    "16":"não",
    "17":"não",
    "18":"sim",
    "19":"sim",
    "20":"sim",
    "21":"não",
    "22":"sim",
    "23":"não",
    "24":"não",
    "25":"não",
    "Personagem":"ariel"
  },
  {
    "0":"sim",
    "1":"não",
    "2":"sim",
    "3":"não",
    "4":"sim",
    "5":"não",
    "6":"não",
    "7":"não",
    "8":"não",
    "9":"não",
    "10":"não",
    "11":"não",
    "12":"não",
    "13":"sim",
    "14":"sim",
    "15":"sim",
    "16":"não",
    "17":"não",
    "18":"sim",
    "19":"não",
    "20":"não",
    "21":"não",
    "22":"não",
    "23":"não",
    "24":"sim",
    "25":"não",
    "Personagem":"athur"
  },
  {
    "0":"sim",
    "1":"não",
    "2":"sim",
    "3":"não",
    "4":"sim",
    "5":"não",
    "6":"não",
    "7":"não",
    "8":"não",
    "9":"não",
    "10":"não",
    "11":"sim",
    "12":"não",
    "13":"não",
    "14":"sim",
    "15":"sim",
    "16":"não",
    "17":"sim",
    "18":"sim",
    "19":"não",
    "20":"não",
    "21":"não",
    "22":"não",
    "23":"não",
    "24":"não",
    "25":"não",
    "Personagem":"atchoum"
  },
  {
    "0":"não",
    "1":"sim",
    "2":"não",
    "3":"não",
    "4":"não",
    "5":"sim",
    "6":"não",
    "7":"não",
    "8":"não",
    "9":"sim",
    "10":"não",
    "11":"sim",
    "12":"sim",
    "13":"sim",
    "14":"não",
    "15":"sim",
    "16":"não",
    "17":"sim",
    "18":"sim",
    "19":"não",
    "20":"não",
    "21":"não",
    "22":"não",
    "23":"não",
    "24":"não",
    "25":"não",
    "Personagem":"bagheera"
  },
  {
    "0":"sim",
    "1":"não",
    "2":"não",
    "3":"não",
    "4":"não",
    "5":"não",
    "6":"sim",
    "7":"não",
    "8":"não",
    "9":"não",
    "10":"não",
    "11":"sim",
    "12":"sim",
    "13":"não",
    "14":"sim",
    "15":"sim",
    "16":"não",
    "17":"sim",
    "18":"sim",
    "19":"não",
    "20":"não",
    "21":"não",
    "22":"não",
    "23":"não",
    "24":"não",
    "25":"não",
    "Personagem":"baloo"
  },
  {
    "0":"sim",
    "1":"não",
    "2":"não",
    "3":"não",
    "4":"sim",
    "5":"não",
    "6":"não",
    "7":"não",
    "8":"não",
    "9":"não",
    "10":"não",
    "11":"não",
    "12":"sim",
    "13":"sim",
    "14":"sim",
    "15":"sim",
    "16":"não",
    "17":"sim",
    "18":"sim",
    "19":"não",
    "20":"não",
    "21":"não",
    "22":"não",
    "23":"não",
    "24":"não",
    "25":"sim",
    "Personagem":"bambi"
  },
  {
    "0":"não",
    "1":"sim",
    "2":"sim",
    "3":"não",
    "4":"não",
    "5":"não",
    "6":"sim",
    "7":"não",
    "8":"não",
    "9":"não",
    "10":"não",
    "11":"sim",
    "12":"não",
    "13":"sim",
    "14":"não",
    "15":"sim",
    "16":"não",
    "17":"não",
    "18":"sim",
    "19":"não",
    "20":"não",
    "21":"não",
    "22":"não",
    "23":"não",
    "24":"não",
    "25":"não",
    "Personagem":"barbie"
  },
  {
    "0":"não",
    "1":"sim",
    "2":"sim",
    "3":"não",
    "4":"não",
    "5":"não",
    "6":"sim",
    "7":"não",
    "8":"não",
    "9":"não",
    "10":"não",
    "11":"sim",
    "12":"não",
    "13":"sim",
    "14":"não",
    "15":"sim",
    "16":"não",
    "17":"não",
    "18":"sim",
    "19":"não",
    "20":"não",
    "21":"não",
    "22":"não",
    "23":"sim",
    "24":"não",
    "25":"não",
    "Personagem":"belle"
  },
  {
    "0":"sim",
    "1":"não",
    "2":"sim",
    "3":"não",
    "4":"não",
    "5":"não",
    "6":"sim",
    "7":"não",
    "8":"não",
    "9":"não",
    "10":"não",
    "11":"sim",
    "12":"sim",
    "13":"sim",
    "14":"não",
    "15":"não",
    "16":"não",
    "17":"sim",
    "18":"sim",
    "19":"não",
    "20":"sim",
    "21":"não",
    "22":"não",
    "23":"não",
    "24":"não",
    "25":"sim",
    "Personagem":"la bete"
  },
  {
    "0":"não",
    "1":"sim",
    "2":"sim",
    "3":"não",
    "4":"não",
    "5":"não",
    "6":"sim",
    "7":"não",
    "8":"não",
    "9":"não",
    "10":"não",
    "11":"sim",
    "12":"não",
    "13":"não",
    "14":"sim",
    "15":"sim",
    "16":"não",
    "17":"não",
    "18":"sim",
    "19":"não",
    "20":"não",
    "21":"não",
    "22":"não",
    "23":"sim",
    "24":"não",
    "25":"não",
    "Personagem":"blanche neige"
  },
  {
    "0":"sim",
    "1":"não",
    "2":"não",
    "3":"não",
    "4":"não",
    "5":"sim",
    "6":"não",
    "7":"não",
    "8":"não",
    "9":"não",
    "10":"não",
    "11":"sim",
    "12":"sim",
    "13":"não",
    "14":"sim",
    "15":"sim",
    "16":"não",
    "17":"sim",
    "18":"sim",
    "19":"não",
    "20":"não",
    "21":"não",
    "22":"não",
    "23":"não",
    "24":"não",
    "25":"não",
    "Personagem":"bourriquet"
  },
  {
    "0":"sim",
    "1":"não",
    "2":"não",
    "3":"sim",
    "4":"sim",
    "5":"não",
    "6":"não",
    "7":"sim",
    "8":"sim",
    "9":"sim",
    "10":"não",
    "11":"sim",
    "12":"não",
    "13":"sim",
    "14":"não",
    "15":"sim",
    "16":"sim",
    "17":"não",
    "18":"sim",
    "19":"não",
    "20":"não",
    "21":"não",
    "22":"sim",
    "23":"não",
    "24":"não",
    "25":"não",
    "Personagem":"buzz l'eclair"
  },
  {
    "0":"sim",
    "1":"não",
    "2":"sim",
    "3":"não",
    "4":"não",
    "5":"não",
    "6":"sim",
    "7":"não",
    "8":"não",
    "9":"sim",
    "10":"não",
    "11":"sim",
    "12":"não",
    "13":"não",
    "14":"não",
    "15":"não",
    "16":"sim",
    "17":"não",
    "18":"sim",
    "19":"não",
    "20":"não",
    "21":"não",
    "22":"não",
    "23":"não",
    "24":"sim",
    "25":"não",
    "Personagem":"capitaine crochet"
  },
  {
    "0":"não",
    "1":"sim",
    "2":"sim",
    "3":"não",
    "4":"não",
    "5":"não",
    "6":"sim",
    "7":"não",
    "8":"não",
    "9":"não",
    "10":"não",
    "11":"sim",
    "12":"não",
    "13":"sim",
    "14":"não",
    "15":"sim",
    "16":"não",
    "17":"não",
    "18":"sim",
    "19":"não",
    "20":"não",
    "21":"não",
    "22":"não",
    "23":"não",
    "24":"não",
    "25":"não",
    "Personagem":"cendrillon"
  },
  {
    "0":"sim",
    "1":"não",
    "2":"não",
    "3":"não",
    "4":"sim",
    "5":"não",
    "6":"não",
    "7":"não",
    "8":"não",
    "9":"não",
    "10":"não",
    "11":"sim",
    "12":"sim",
    "13":"sim",
    "14":"sim",
    "15":"sim",
    "16":"não",
    "17":"sim",
    "18":"sim",
    "19":"não",
    "20":"não",
    "21":"não",
    "22":"não",
    "23":"não",
    "24":"não",
    "25":"não",
    "Personagem":"clochard"
  },
  {
    "0":"sim",
    "1":"não",
    "2":"não",
    "3":"não",
    "4":"não",
    "5":"não",
    "6":"sim",
    "7":"não",
    "8":"não",
    "9":"não",
    "10":"não",
    "11":"sim",
    "12":"sim",
    "13":"não",
    "14":"sim",
    "15":"sim",
    "16":"não",
    "17":"sim",
    "18":"sim",
    "19":"não",
    "20":"não",
    "21":"sim",
    "22":"não",
    "23":"não",
    "24":"não",
    "25":"não",
    "Personagem":"coco lapin"
  },
  {
    "0":"não",
    "1":"sim",
    "2":"não",
    "3":"não",
    "4":"sim",
    "5":"não",
    "6":"não",
    "7":"não",
    "8":"não",
    "9":"não",
    "10":"não",
    "11":"sim",
    "12":"sim",
    "13":"sim",
    "14":"não",
    "15":"sim",
    "16":"não",
    "17":"não",
    "18":"sim",
    "19":"não",
    "20":"não",
    "21":"não",
    "22":"não",
    "23":"sim",
    "24":"não",
    "25":"não",
    "Personagem":"daisy"
  },
  {
    "0":"sim",
    "1":"não",
    "2":"não",
    "3":"não",
    "4":"não",
    "5":"não",
    "6":"sim",
    "7":"não",
    "8":"não",
    "9":"não",
    "10":"não",
    "11":"sim",
    "12":"sim",
    "13":"não",
    "14":"sim",
    "15":"sim",
    "16":"não",
    "17":"sim",
    "18":"sim",
    "19":"não",
    "20":"não",
    "21":"não",
    "22":"não",
    "23":"não",
    "24":"não",
    "25":"não",
    "Personagem":"dinguo"
  },
  {
    "0":"sim",
    "1":"não",
    "2":"não",
    "3":"não",
    "4":"sim",
    "5":"não",
    "6":"não",
    "7":"não",
    "8":"não",
    "9":"não",
    "10":"não",
    "11":"sim",
    "12":"sim",
    "13":"não",
    "14":"sim",
    "15":"sim",
    "16":"não",
    "17":"não",
    "18":"sim",
    "19":"não",
    "20":"não",
    "21":"não",
    "22":"não",
    "23":"sim",
    "24":"não",
    "25":"não",
    "Personagem":"donald"
  },
  {
    "0":"sim",
    "1":"não",
    "2":"sim",
    "3":"não",
    "4":"sim",
    "5":"não",
    "6":"não",
    "7":"não",
    "8":"não",
    "9":"não",
    "10":"não",
    "11":"sim",
    "12":"não",
    "13":"não",
    "14":"sim",
    "15":"sim",
    "16":"não",
    "17":"sim",
    "18":"sim",
    "19":"não",
    "20":"não",
    "21":"não",
    "22":"não",
    "23":"não",
    "24":"não",
    "25":"não",
    "Personagem":"dormeur"
  },
  {
    "0":"sim",
    "1":"não",
    "2":"não",
    "3":"não",
    "4":"sim",
    "5":"não",
    "6":"não",
    "7":"não",
    "8":"sim",
    "9":"não",
    "10":"não",
    "11":"não",
    "12":"sim",
    "13":"sim",
    "14":"sim",
    "15":"sim",
    "16":"não",
    "17":"sim",
    "18":"sim",
    "19":"não",
    "20":"não",
    "21":"não",
    "22":"não",
    "23":"não",
    "24":"não",
    "25":"não",
    "Personagem":"dumbo"
  },
  {
    "0":"não",
    "1":"sim",
    "2":"sim",
    "3":"não",
    "4":"não",
    "5":"sim",
    "6":"não",
    "7":"sim",
    "8":"não",
    "9":"não",
    "10":"não",
    "11":"não",
    "12":"não",
    "13":"sim",
    "14":"sim",
    "15":"sim",
    "16":"não",
    "17":"não",
    "18":"sim",
    "19":"não",
    "20":"sim",
    "21":"não",
    "22":"não",
    "23":"não",
    "24":"não",
    "25":"não",
    "Personagem":"elsa"
  },
  {
    "0":"não",
    "1":"sim",
    "2":"não",
    "3":"não",
    "4":"sim",
    "5":"não",
    "6":"não",
    "7":"sim",
    "8":"sim",
    "9":"não",
    "10":"não",
    "11":"sim",
    "12":"não",
    "13":"sim",
    "14":"sim",
    "15":"sim",
    "16":"não",
    "17":"não",
    "18":"sim",
    "19":"não",
    "20":"não",
    "21":"não",
    "22":"não",
    "23":"não",
    "24":"não",
    "25":"não",
    "Personagem":"fee clochette"
  },
  {
    "0":"sim",
    "1":"não",
    "2":"não",
    "3":"não",
    "4":"não",
    "5":"não",
    "6":"sim",
    "7":"sim",
    "8":"sim",
    "9":"sim",
    "10":"não",
    "11":"sim",
    "12":"não",
    "13":"sim",
    "14":"sim",
    "15":"sim",
    "16":"sim",
    "17":"não",
    "18":"sim",
    "19":"não",
    "20":"não",
    "21":"não",
    "22":"não",
    "23":"sim",
    "24":"não",
    "25":"não",
    "Personagem":"le genie"
  },
  {
    "0":"sim",
    "1":"não",
    "2":"sim",
    "3":"não",
    "4":"não",
    "5":"sim",
    "6":"não",
    "7":"não",
    "8":"não",
    "9":"não",
    "10":"não",
    "11":"sim",
    "12":"não",
    "13":"sim",
    "14":"não",
    "15":"sim",
    "16":"não",
    "17":"não",
    "18":"sim",
    "19":"não",
    "20":"não",
    "21":"não",
    "22":"não",
    "23":"não",
    "24":"não",
    "25":"não",
    "Personagem":"geppetto"
  },
  {
    "0":"sim",
    "1":"não",
    "2":"sim",
    "3":"não",
    "4":"sim",
    "5":"não",
    "6":"não",
    "7":"não",
    "8":"não",
    "9":"não",
    "10":"não",
    "11":"sim",
    "12":"não",
    "13":"sim",
    "14":"não",
    "15":"não",
    "16":"não",
    "17":"sim",
    "18":"sim",
    "19":"não",
    "20":"não",
    "21":"não",
    "22":"não",
    "23":"não",
    "24":"não",
    "25":"não",
    "Personagem":"grincheux"
  },
  {
    "0":"sim",
    "1":"não",
    "2":"não",
    "3":"não",
    "4":"sim",
    "5":"não",
    "6":"não",
    "7":"não",
    "8":"não",
    "9":"não",
    "10":"não",
    "11":"sim",
    "12":"sim",
    "13":"sim",
    "14":"não",
    "15":"não",
    "16":"não",
    "17":"não",
    "18":"sim",
    "19":"não",
    "20":"não",
    "21":"não",
    "22":"não",
    "23":"não",
    "24":"não",
    "25":"não",
    "Personagem":"gripsou"
  },
  {
    "0":"sim",
    "1":"não",
    "2":"sim",
    "3":"sim",
    "4":"não",
    "5":"não",
    "6":"sim",
    "7":"não",
    "8":"não",
    "9":"sim",
    "10":"sim",
    "11":"sim",
    "12":"não",
    "13":"sim",
    "14":"sim",
    "15":"sim",
    "16":"sim",
    "17":"não",
    "18":"sim",
    "19":"não",
    "20":"não",
    "21":"não",
    "22":"não",
    "23":"não",
    "24":"não",
    "25":"não",
    "Personagem":"hercule"
  },
  {
    "0":"desconhecido",
    "1":"desconhecido",
    "2":"não",
    "3":"não",
    "4":"não",
    "5":"não",
    "6":"sim",
    "7":"sim",
    "8":"sim",
    "9":"sim",
    "10":"não",
    "11":"sim",
    "12":"sim",
    "13":"não",
    "14":"não",
    "15":"não",
    "16":"sim",
    "17":"não",
    "18":"não",
    "19":"não",
    "20":"sim",
    "21":"não",
    "22":"não",
    "23":"não",
    "24":"não",
    "25":"não",
    "Personagem":"hydre"
  },
  {
    "0":"sim",
    "1":"não",
    "2":"sim",
    "3":"não",
    "4":"não",
    "5":"não",
    "6":"sim",
    "7":"sim",
    "8":"não",
    "9":"sim",
    "10":"sim",
    "11":"sim",
    "12":"não",
    "13":"sim",
    "14":"não",
    "15":"não",
    "16":"sim",
    "17":"não",
    "18":"sim",
    "19":"não",
    "20":"sim",
    "21":"não",
    "22":"não",
    "23":"não",
    "24":"não",
    "25":"não",
    "Personagem":"jafar"
  },
  {
    "0":"não",
    "1":"sim",
    "2":"sim",
    "3":"não",
    "4":"não",
    "5":"sim",
    "6":"não",
    "7":"não",
    "8":"não",
    "9":"não",
    "10":"não",
    "11":"sim",
    "12":"não",
    "13":"sim",
    "14":"não",
    "15":"sim",
    "16":"não",
    "17":"não",
    "18":"sim",
    "19":"não",
    "20":"não",
    "21":"não",
    "22":"não",
    "23":"não",
    "24":"não",
    "25":"não",
    "Personagem":"jasmine"
  },
  {
    "0":"não",
    "1":"sim",
    "2":"não",
    "3":"não",
    "4":"sim",
    "5":"não",
    "6":"não",
    "7":"não",
    "8":"não",
    "9":"não",
    "10":"não",
    "11":"sim",
    "12":"não",
    "13":"sim",
    "14":"não",
    "15":"sim",
    "16":"sim",
    "17":"não",
    "18":"sim",
    "19":"não",
    "20":"não",
    "21":"sim",
    "22":"não",
    "23":"não",
    "24":"não",
    "25":"não",
    "Personagem":"jessie"
  },
  {
    "0":"sim",
    "1":"não",
    "2":"não",
    "3":"não",
    "4":"sim",
    "5":"não",
    "6":"não",
    "7":"não",
    "8":"não",
    "9":"não",
    "10":"não",
    "11":"sim",
    "12":"sim",
    "13":"sim",
    "14":"não",
    "15":"sim",
    "16":"não",
    "17":"não",
    "18":"sim",
    "19":"não",
    "20":"não",
    "21":"não",
    "22":"sim",
    "23":"não",
    "24":"não",
    "25":"não",
    "Personagem":"jiminy cricket"
  },
  {
    "0":"sim",
    "1":"não",
    "2":"sim",
    "3":"não",
    "4":"sim",
    "5":"não",
    "6":"não",
    "7":"não",
    "8":"não",
    "9":"não",
    "10":"não",
    "11":"sim",
    "12":"não",
    "13":"sim",
    "14":"sim",
    "15":"sim",
    "16":"não",
    "17":"sim",
    "18":"sim",
    "19":"não",
    "20":"não",
    "21":"não",
    "22":"não",
    "23":"não",
    "24":"não",
    "25":"não",
    "Personagem":"joyeux"
  },
  {
    "0":"sim",
    "1":"não",
    "2":"sim",
    "3":"não",
    "4":"não",
    "5":"não",
    "6":"sim",
    "7":"não",
    "8":"não",
    "9":"não",
    "10":"não",
    "11":"sim",
    "12":"não",
    "13":"sim",
    "14":"não",
    "15":"sim",
    "16":"não",
    "17":"não",
    "18":"sim",
    "19":"não",
    "20":"não",
    "21":"não",
    "22":"não",
    "23":"não",
    "24":"não",
    "25":"não",
    "Personagem":"ken"
  },
  {
    "0":"sim",
    "1":"não",
    "2":"sim",
    "3":"não",
    "4":"não",
    "5":"sim",
    "6":"não",
    "7":"não",
    "8":"não",
    "9":"não",
    "10":"não",
    "11":"sim",
    "12":"não",
    "13":"não",
    "14":"sim",
    "15":"não",
    "16":"não",
    "17":"não",
    "18":"sim",
    "19":"não",
    "20":"não",
    "21":"não",
    "22":"não",
    "23":"não",
    "24":"não",
    "25":"não",
    "Personagem":"kuzco"
  },
  {
    "0":"não",
    "1":"sim",
    "2":"não",
    "3":"não",
    "4":"sim",
    "5":"não",
    "6":"não",
    "7":"não",
    "8":"não",
    "9":"não",
    "10":"não",
    "11":"não",
    "12":"sim",
    "13":"sim",
    "14":"sim",
    "15":"sim",
    "16":"não",
    "17":"sim",
    "18":"sim",
    "19":"não",
    "20":"não",
    "21":"não",
    "22":"não",
    "23":"não",
    "24":"não",
    "25":"sim",
    "Personagem":"lady"
  },
  {
    "0":"não",
    "1":"sim",
    "2":"não",
    "3":"não",
    "4":"sim",
    "5":"não",
    "6":"não",
    "7":"não",
    "8":"não",
    "9":"não",
    "10":"não",
    "11":"sim",
    "12":"não",
    "13":"não",
    "14":"sim",
    "15":"sim",
    "16":"não",
    "17":"não",
    "18":"sim",
    "19":"não",
    "20":"sim",
    "21":"não",
    "22":"não",
    "23":"não",
    "24":"não",
    "25":"sim",
    "Personagem":"madame patate"
  },
  {
    "0":"sim",
    "1":"não",
    "2":"sim",
    "3":"não",
    "4":"não",
    "5":"não",
    "6":"sim",
    "7":"sim",
    "8":"não",
    "9":"não",
    "10":"sim",
    "11":"sim",
    "12":"não",
    "13":"sim",
    "14":"não",
    "15":"sim",
    "16":"sim",
    "17":"não",
    "18":"sim",
    "19":"não",
    "20":"sim",
    "21":"não",
    "22":"não",
    "23":"sim",
    "24":"não",
    "25":"não",
    "Personagem":"merlin"
  },
  {
    "0":"sim",
    "1":"não",
    "2":"não",
    "3":"não",
    "4":"sim",
    "5":"não",
    "6":"não",
    "7":"não",
    "8":"não",
    "9":"não",
    "10":"não",
    "11":"sim",
    "12":"sim",
    "13":"sim",
    "14":"sim",
    "15":"sim",
    "16":"não",
    "17":"não",
    "18":"sim",
    "19":"não",
    "20":"não",
    "21":"não",
    "22":"não",
    "23":"não",
    "24":"sim",
    "25":"não",
    "Personagem":"mickey"
  },
  {
    "0":"sim",
    "1":"não",
    "2":"não",
    "3":"não",
    "4":"sim",
    "5":"não",
    "6":"não",
    "7":"não",
    "8":"não",
    "9":"não",
    "10":"não",
    "11":"sim",
    "12":"não",
    "13":"não",
    "14":"sim",
    "15":"sim",
    "16":"não",
    "17":"não",
    "18":"sim",
    "19":"não",
    "20":"sim",
    "21":"não",
    "22":"não",
    "23":"não",
    "24":"não",
    "25":"sim",
    "Personagem":"monsieur patate"
  },
  {
    "0":"sim",
    "1":"não",
    "2":"sim",
    "3":"não",
    "4":"não",
    "5":"sim",
    "6":"não",
    "7":"não",
    "8":"não",
    "9":"não",
    "10":"não",
    "11":"não",
    "12":"não",
    "13":"não",
    "14":"sim",
    "15":"sim",
    "16":"não",
    "17":"não",
    "18":"sim",
    "19":"não",
    "20":"não",
    "21":"não",
    "22":"não",
    "23":"não",
    "24":"não",
    "25":"sim",
    "Personagem":"mowgli"
  },
  {
    "0":"sim",
    "1":"não",
    "2":"não",
    "3":"não",
    "4":"não",
    "5":"não",
    "6":"sim",
    "7":"não",
    "8":"não",
    "9":"sim",
    "10":"não",
    "11":"sim",
    "12":"sim",
    "13":"sim",
    "14":"não",
    "15":"sim",
    "16":"sim",
    "17":"sim",
    "18":"sim",
    "19":"não",
    "20":"não",
    "21":"sim",
    "22":"não",
    "23":"não",
    "24":"não",
    "25":"sim",
    "Personagem":"mufasa"
  },
  {
    "0":"não",
    "1":"sim",
    "2":"não",
    "3":"não",
    "4":"sim",
    "5":"não",
    "6":"não",
    "7":"não",
    "8":"não",
    "9":"não",
    "10":"não",
    "11":"não",
    "12":"sim",
    "13":"sim",
    "14":"não",
    "15":"sim",
    "16":"não",
    "17":"sim",
    "18":"sim",
    "19":"não",
    "20":"não",
    "21":"sim",
    "22":"não",
    "23":"não",
    "24":"não",
    "25":"não",
    "Personagem":"nala"
  },
  {
    "0":"sim",
    "1":"não",
    "2":"não",
    "3":"não",
    "4":"sim",
    "5":"não",
    "6":"não",
    "7":"não",
    "8":"não",
    "9":"não",
    "10":"não",
    "11":"não",
    "12":"sim",
    "13":"sim",
    "14":"sim",
    "15":"sim",
    "16":"não",
    "17":"não",
    "18":"sim",
    "19":"sim",
    "20":"não",
    "21":"não",
    "22":"não",
    "23":"não",
    "24":"sim",
    "25":"não",
    "Personagem":"nemo"
  },
  {
    "0":"sim",
    "1":"não",
    "2":"não",
    "3":"não",
    "4":"sim",
    "5":"não",
    "6":"não",
    "7":"não",
    "8":"não",
    "9":"não",
    "10":"não",
    "11":"não",
    "12":"sim",
    "13":"sim",
    "14":"sim",
    "15":"sim",
    "16":"não",
    "17":"sim",
    "18":"sim",
    "19":"não",
    "20":"não",
    "21":"não",
    "22":"não",
    "23":"não",
    "24":"não",
    "25":"não",
    "Personagem":"pan-pan"
  },
  {
    "0":"sim",
    "1":"não",
    "2":"sim",
    "3":"não",
    "4":"não",
    "5":"sim",
    "6":"não",
    "7":"não",
    "8":"sim",
    "9":"sim",
    "10":"não",
    "11":"não",
    "12":"não",
    "13":"sim",
    "14":"sim",
    "15":"sim",
    "16":"sim",
    "17":"não",
    "18":"sim",
    "19":"não",
    "20":"não",
    "21":"não",
    "22":"sim",
    "23":"não",
    "24":"não",
    "25":"não",
    "Personagem":"peter pan"
  },
  {
    "0":"sim",
    "1":"não",
    "2":"não",
    "3":"não",
    "4":"sim",
    "5":"não",
    "6":"não",
    "7":"não",
    "8":"não",
    "9":"não",
    "10":"não",
    "11":"não",
    "12":"não",
    "13":"não",
    "14":"sim",
    "15":"sim",
    "16":"não",
    "17":"não",
    "18":"sim",
    "19":"não",
    "20":"sim",
    "21":"sim",
    "22":"não",
    "23":"não",
    "24":"não",
    "25":"não",
    "Personagem":"pinocchio"
  },
  {
    "0":"sim",
    "1":"não",
    "2":"não",
    "3":"não",
    "4":"não",
    "5":"sim",
    "6":"não",
    "7":"não",
    "8":"não",
    "9":"não",
    "10":"não",
    "11":"sim",
    "12":"sim",
    "13":"não",
    "14":"sim",
    "15":"sim",
    "16":"não",
    "17":"sim",
    "18":"sim",
    "19":"não",
    "20":"não",
    "21":"sim",
    "22":"não",
    "23":"não",
    "24":"não",
    "25":"não",
    "Personagem":"pluto"
  },
  {
    "0":"sim",
    "1":"não",
    "2":"não",
    "3":"não",
    "4":"sim",
    "5":"não",
    "6":"não",
    "7":"não",
    "8":"não",
    "9":"não",
    "10":"não",
    "11":"não",
    "12":"sim",
    "13":"não",
    "14":"sim",
    "15":"sim",
    "16":"não",
    "17":"não",
    "18":"sim",
    "19":"não",
    "20":"não",
    "21":"não",
    "22":"não",
    "23":"não",
    "24":"não",
    "25":"não",
    "Personagem":"porcinet"
  },
  {
    "0":"sim",
    "1":"não",
    "2":"sim",
    "3":"não",
    "4":"sim",
    "5":"não",
    "6":"não",
    "7":"não",
    "8":"não",
    "9":"não",
    "10":"não",
    "11":"sim",
    "12":"não",
    "13":"sim",
    "14":"não",
    "15":"sim",
    "16":"não",
    "17":"sim",
    "18":"sim",
    "19":"não",
    "20":"não",
    "21":"não",
    "22":"não",
    "23":"não",
    "24":"não",
    "25":"não",
    "Personagem":"prof"
  },
  {
    "0":"sim",
    "1":"não",
    "2":"não",
    "3":"não",
    "4":"sim",
    "5":"não",
    "6":"não",
    "7":"não",
    "8":"não",
    "9":"não",
    "10":"não",
    "11":"sim",
    "12":"sim",
    "13":"não",
    "14":"sim",
    "15":"sim",
    "16":"não",
    "17":"sim",
    "18":"sim",
    "19":"não",
    "20":"não",
    "21":"não",
    "22":"não",
    "23":"não",
    "24":"não",
    "25":"sim",
    "Personagem":"pumbaa"
  },
  {
    "0":"sim",
    "1":"não",
    "2":"sim",
    "3":"não",
    "4":"não",
    "5":"sim",
    "6":"não",
    "7":"não",
    "8":"não",
    "9":"sim",
    "10":"não",
    "11":"sim",
    "12":"não",
    "13":"sim",
    "14":"sim",
    "15":"sim",
    "16":"não",
    "17":"não",
    "18":"sim",
    "19":"não",
    "20":"não",
    "21":"não",
    "22":"sim",
    "23":"não",
    "24":"não",
    "25":"não",
    "Personagem":"quasimodo"
  },
  {
    "0":"sim",
    "1":"não",
    "2":"não",
    "3":"não",
    "4":"sim",
    "5":"não",
    "6":"não",
    "7":"não",
    "8":"não",
    "9":"não",
    "10":"não",
    "11":"não",
    "12":"sim",
    "13":"sim",
    "14":"sim",
    "15":"sim",
    "16":"não",
    "17":"não",
    "18":"sim",
    "19":"não",
    "20":"não",
    "21":"não",
    "22":"sim",
    "23":"sim",
    "24":"sim",
    "25":"não",
    "Personagem":"riri fifi loulou"
  },
  {
    "0":"sim",
    "1":"não",
    "2":"não",
    "3":"não",
    "4":"não",
    "5":"sim",
    "6":"não",
    "7":"não",
    "8":"não",
    "9":"sim",
    "10":"não",
    "11":"sim",
    "12":"sim",
    "13":"sim",
    "14":"sim",
    "15":"sim",
    "16":"sim",
    "17":"sim",
    "18":"sim",
    "19":"não",
    "20":"não",
    "21":"não",
    "22":"sim",
    "23":"não",
    "24":"não",
    "25":"sim",
    "Personagem":"robin des bois"
  },
  {
    "0":"sim",
    "1":"não",
    "2":"não",
    "3":"não",
    "4":"sim",
    "5":"não",
    "6":"não",
    "7":"não",
    "8":"não",
    "9":"não",
    "10":"não",
    "11":"não",
    "12":"sim",
    "13":"sim",
    "14":"sim",
    "15":"sim",
    "16":"não",
    "17":"sim",
    "18":"sim",
    "19":"não",
    "20":"não",
    "21":"não",
    "22":"não",
    "23":"não",
    "24":"não",
    "25":"sim",
    "Personagem":"rouky"
  },
  {
    "0":"sim",
    "1":"não",
    "2":"não",
    "3":"não",
    "4":"sim",
    "5":"não",
    "6":"não",
    "7":"não",
    "8":"não",
    "9":"não",
    "10":"não",
    "11":"não",
    "12":"sim",
    "13":"sim",
    "14":"sim",
    "15":"sim",
    "16":"não",
    "17":"sim",
    "18":"sim",
    "19":"não",
    "20":"não",
    "21":"não",
    "22":"não",
    "23":"não",
    "24":"não",
    "25":"sim",
    "Personagem":"rox"
  },
  {
    "0":"sim",
    "1":"não",
    "2":"não",
    "3":"não",
    "4":"não",
    "5":"não",
    "6":"sim",
    "7":"não",
    "8":"não",
    "9":"sim",
    "10":"não",
    "11":"sim",
    "12":"sim",
    "13":"sim",
    "14":"não",
    "15":"não",
    "16":"sim",
    "17":"sim",
    "18":"sim",
    "19":"não",
    "20":"não",
    "21":"não",
    "22":"não",
    "23":"não",
    "24":"não",
    "25":"sim",
    "Personagem":"scar"
  },
  {
    "0":"sim",
    "1":"não",
    "2":"não",
    "3":"não",
    "4":"não",
    "5":"não",
    "6":"sim",
    "7":"não",
    "8":"não",
    "9":"sim",
    "10":"não",
    "11":"sim",
    "12":"sim",
    "13":"sim",
    "14":"não",
    "15":"não",
    "16":"sim",
    "17":"sim",
    "18":"sim",
    "19":"não",
    "20":"não",
    "21":"não",
    "22":"não",
    "23":"não",
    "24":"não",
    "25":"sim",
    "Personagem":"shere khan"
  },
  {
    "0":"sim",
    "1":"não",
    "2":"não",
    "3":"não",
    "4":"sim",
    "5":"não",
    "6":"não",
    "7":"não",
    "8":"não",
    "9":"sim",
    "10":"não",
    "11":"não",
    "12":"sim",
    "13":"sim",
    "14":"sim",
    "15":"sim",
    "16":"não",
    "17":"sim",
    "18":"sim",
    "19":"não",
    "20":"não",
    "21":"não",
    "22":"não",
    "23":"não",
    "24":"não",
    "25":"sim",
    "Personagem":"simba"
  },
  {
    "0":"sim",
    "1":"não",
    "2":"sim",
    "3":"não",
    "4":"sim",
    "5":"não",
    "6":"não",
    "7":"não",
    "8":"não",
    "9":"não",
    "10":"não",
    "11":"não",
    "12":"não",
    "13":"não",
    "14":"sim",
    "15":"sim",
    "16":"não",
    "17":"não",
    "18":"não",
    "19":"não",
    "20":"não",
    "21":"não",
    "22":"sim",
    "23":"não",
    "24":"não",
    "25":"não",
    "Personagem":"simplet"
  },
  {
    "0":"desconhecido",
    "1":"desconhecido",
    "2":"não",
    "3":"não",
    "4":"não",
    "5":"sim",
    "6":"não",
    "7":"não",
    "8":"sim",
    "9":"não",
    "10":"não",
    "11":"desconhecido",
    "12":"não",
    "13":"desconhecido",
    "14":"não",
    "15":"sim",
    "16":"não",
    "17":"não",
    "18":"não",
    "19":"não",
    "20":"não",
    "21":"não",
    "22":"não",
    "23":"sim",
    "24":"não",
    "25":"não",
    "Personagem":"tapis magique"
  },
  {
    "0":"sim",
    "1":"não",
    "2":"não",
    "3":"não",
    "4":"não",
    "5":"não",
    "6":"sim",
    "7":"não",
    "8":"não",
    "9":"não",
    "10":"não",
    "11":"sim",
    "12":"sim",
    "13":"não",
    "14":"sim",
    "15":"sim",
    "16":"não",
    "17":"sim",
    "18":"sim",
    "19":"não",
    "20":"não",
    "21":"não",
    "22":"não",
    "23":"não",
    "24":"não",
    "25":"não",
    "Personagem":""
  },
  {
    "0":"sim",
    "1":"não",
    "2":"sim",
    "3":"não",
    "4":"sim",
    "5":"não",
    "6":"não",
    "7":"não",
    "8":"não",
    "9":"não",
    "10":"não",
    "11":"sim",
    "12":"não",
    "13":"não",
    "14":"não",
    "15":"sim",
    "16":"não",
    "17":"sim",
    "18":"sim",
    "19":"não",
    "20":"não",
    "21":"não",
    "22":"não",
    "23":"não",
    "24":"não",
    "25":"não",
    "Personagem":"timide"
  },
  {
    "0":"sim",
    "1":"não",
    "2":"não",
    "3":"não",
    "4":"sim",
    "5":"não",
    "6":"não",
    "7":"não",
    "8":"não",
    "9":"não",
    "10":"não",
    "11":"sim",
    "12":"sim",
    "13":"sim",
    "14":"sim",
    "15":"sim",
    "16":"não",
    "17":"sim",
    "18":"sim",
    "19":"não",
    "20":"não",
    "21":"não",
    "22":"não",
    "23":"não",
    "24":"não",
    "25":"sim",
    "Personagem":"timon"
  },
  {
    "0":"sim",
    "1":"não",
    "2":"não",
    "3":"não",
    "4":"sim",
    "5":"não",
    "6":"não",
    "7":"não",
    "8":"não",
    "9":"não",
    "10":"não",
    "11":"não",
    "12":"sim",
    "13":"não",
    "14":"sim",
    "15":"sim",
    "16":"não",
    "17":"sim",
    "18":"sim",
    "19":"não",
    "20":"não",
    "21":"sim",
    "22":"não",
    "23":"não",
    "24":"sim",
    "25":"não",
    "Personagem":"winnie l'ourson"
  },
  {
    "0":"sim",
    "1":"não",
    "2":"não",
    "3":"sim",
    "4":"sim",
    "5":"não",
    "6":"não",
    "7":"não",
    "8":"não",
    "9":"não",
    "10":"não",
    "11":"sim",
    "12":"não",
    "13":"sim",
    "14":"não",
    "15":"sim",
    "16":"sim",
    "17":"não",
    "18":"sim",
    "19":"não",
    "20":"não",
    "21":"sim",
    "22":"não",
    "23":"não",
    "24":"não",
    "25":"sim",
    "Personagem":"woody"
  }
]